cochleogram/__init__.py
cochleogram/config.py
cochleogram/gui.enaml
cochleogram/instructions.html
cochleogram/main.py
cochleogram/model.py
cochleogram/plot.py
cochleogram/presenter.py
cochleogram/readers.py
cochleogram/util.py
cochleogram/version.py
cochleogram/icons/__init__.py
cochleogram/icons/cells.png
cochleogram/icons/exclude.png
cochleogram/icons/main-icon.ico
cochleogram/icons/main-icon.png
cochleogram/icons/make_icons.py
cochleogram/icons/spiral.png
cochleogram/icons/tile.png
cochleogram-0.10.3.dist-info/METADATA
cochleogram-0.10.3.dist-info/WHEEL
cochleogram-0.10.3.dist-info/entry_points.txt
cochleogram-0.10.3.dist-info/top_level.txt
cochleogram-0.10.3.dist-info/RECORD
