Metadata-Version: 2.4
Name: cochleogram
Version: 0.10.3
Summary: Module for creating cochleograms from confocal images
Author-email: Brad Buran <buran@ohsu.edu>
Maintainer-email: Brad Buran <buran@ohsu.edu>
Requires-Python: >=3.7
Requires-Dist: atom
Requires-Dist: enaml[qt6-pyside]
Requires-Dist: matplotlib
Requires-Dist: ndimage-enaml>=0.0.11
Requires-Dist: numpy
Requires-Dist: pandas
Requires-Dist: scipy
Requires-Dist: scikit-image
Requires-Dist: psiaudio
Provides-Extra: czi
Requires-Dist: aicspylibczi; extra == "czi"
Provides-Extra: lif
Requires-Dist: readlif; extra == "lif"
Provides-Extra: dev
Requires-Dist: docutils; extra == "dev"
